manim_studio/__init__.py
manim_studio/__main__.py
manim_studio/api.py
manim_studio/input_widgets/__init__.py
manim_studio/input_widgets/color_picker.py
manim_studio/input_widgets/range_slider.py
manim_studio/mobject_picker.py
manim_studio/preview.py
manim_studio/syntax_highlighting.py
manim_studio/utils.py
manim_studio/window.py
manim_studio-0.7.4.dist-info/METADATA
manim_studio-0.7.4.dist-info/WHEEL
manim_studio-0.7.4.dist-info/entry_points.txt
manim_studio-0.7.4.dist-info/RECORD
