Metadata-Version: 2.1
Name: manim-studio
Version: 0.7.4
Summary: A GUI for Manim
Author: MathItYT
Author-email: benjamin.ubilla@uc.cl
Requires-Python: >=3.9,<3.13
Classifier: Programming Language :: Python :: 3
Classifier: Programming Language :: Python :: 3.9
Classifier: Programming Language :: Python :: 3.10
Classifier: Programming Language :: Python :: 3.11
Classifier: Programming Language :: Python :: 3.12
Requires-Dist: manim (>=0.18.0,<0.19.0)
Requires-Dist: pyqt6 (>=6.6.1,<7.0.0)
Requires-Dist: setuptools (>=69.1.1,<70.0.0)
